bankid/__init__.py
bankid/__version__.py
bankid/asyncclient.py
bankid/baseclient.py
bankid/certutils.py
bankid/exceptions.py
bankid/qr.py
bankid/responses.py
bankid/syncclient.py
bankid/certs/FPTestcert5_20240610.p12
bankid/certs/FPTestcert5_20240610.pem
bankid/certs/FPTestcert5_20240610_cert.pem
bankid/certs/FPTestcert5_20240610_key.pem
bankid/certs/__init__.py
bankid/certs/appapi.bankid.com.pem
bankid/certs/appapi.test.bankid.com.pem
bankid/certs/appapi2.bankid.com.pem
bankid/certs/appapi2.test.bankid.com.pem
bankid/experimental/__init__.py
bankid/experimental/helper.py
bankid/experimental/verify.py
pybankid-1.5.0.dist-info/LICENSE
pybankid-1.5.0.dist-info/METADATA
pybankid-1.5.0.dist-info/WHEEL
pybankid-1.5.0.dist-info/top_level.txt
pybankid-1.5.0.dist-info/RECORD
