Metadata-Version: 2.2
Name: pybankid
Version: 1.5.0
Summary: BankID Relying Party client for Python
Home-page: https://github.com/hbldh/pybankid
Author: Henrik Blidh
Author-email: henrik.blidh@nedomkull.com
License: MIT
Classifier: Programming Language :: Python
Classifier: Programming Language :: Python :: 3
Classifier: License :: OSI Approved :: MIT License
Classifier: Operating System :: POSIX :: Linux
Classifier: Operating System :: Microsoft :: Windows
Classifier: Operating System :: MacOS :: MacOS X
Classifier: Development Status :: 4 - Beta
Classifier: Intended Audience :: Developers
Classifier: Topic :: Security
Classifier: Topic :: Utilities
License-File: LICENSE
Requires-Dist: httpx
Requires-Dist: importlib_resources; python_version < "3.9"
Provides-Extra: signature-verification
Requires-Dist: asn1crypto; extra == "signature-verification"
Requires-Dist: pytz; extra == "signature-verification"
Requires-Dist: pyOpenSSL; extra == "signature-verification"
Dynamic: author
Dynamic: author-email
Dynamic: classifier
Dynamic: description
Dynamic: description-content-type
Dynamic: home-page
Dynamic: license
Dynamic: provides-extra
Dynamic: requires-dist
Dynamic: summary
